dsdev_utils/__init__.py
dsdev_utils/_version.py
dsdev_utils/app.py
dsdev_utils/compat.py
dsdev_utils/config.py
dsdev_utils/crypto.py
dsdev_utils/exceptions.py
dsdev_utils/helpers.py
dsdev_utils/logger.py
dsdev_utils/paths.py
dsdev_utils/system.py
dsdev_utils/terminal.py
dsdev_utils-0.9.0.dist-info/DESCRIPTION.rst
dsdev_utils-0.9.0.dist-info/METADATA
dsdev_utils-0.9.0.dist-info/RECORD
dsdev_utils-0.9.0.dist-info/WHEEL
dsdev_utils-0.9.0.dist-info/metadata.json
dsdev_utils-0.9.0.dist-info/top_level.txt
